absorptionlib/__init__.py
absorptionlib/setup.py
absorptionlib/CaCl2/__init__.py
absorptionlib/CaCl2/functions.py
absorptionlib/LiBr/__init__.py
absorptionlib/LiBr/functions.py
absorptionlib/LiCl/__init__.py
absorptionlib/LiCl/functions.py
absorptionlib/NaOH/__init__.py
absorptionlib/NaOH/functions.py
absorptionlib-1.0.14.dist-info/LICENSE.txt
absorptionlib-1.0.14.dist-info/METADATA
absorptionlib-1.0.14.dist-info/WHEEL
absorptionlib-1.0.14.dist-info/top_level.txt
absorptionlib-1.0.14.dist-info/RECORD
