Metadata-Version: 2.1
Name: absorptionlib
Version: 1.0.14
Summary: A package for substance properties for absorption systems
Home-page: UNKNOWN
Author: Dorian Höffner
Author-email: dorian.hoeffner@tu-berlin.de
License: UNKNOWN
Platform: UNKNOWN
Classifier: Programming Language :: Python :: 3
Classifier: License :: OSI Approved :: MIT License
Classifier: Operating System :: OS Independent
Requires-Python: >=3.6
License-File: LICENSE.txt
Requires-Dist: numpy
Requires-Dist: matplotlib
Requires-Dist: pyXSteam
Requires-Dist: scipy
Requires-Dist: coolprop
